cas_client/__init__.py
cas_client/_version.py
cas_client/cas_client.py
cas_client-1.0.0.dist-info/LICENSE
cas_client-1.0.0.dist-info/METADATA
cas_client-1.0.0.dist-info/WHEEL
cas_client-1.0.0.dist-info/top_level.txt
cas_client-1.0.0.dist-info/RECORD
