Metadata-Version: 2.1
Name: cas-client
Version: 1.0.0
Summary: A Python CAS client
Home-page: https://github.com/discogs/python-cas-client
Author: Josiah Wolf Oberholtzer
Author-email: joberholtzer@discogsinc.com
License: MIT
Keywords: auth,authentication,cas,cas2,cas3,client,single sign-on,sso
Platform: any
Classifier: Development Status :: 4 - Beta
Classifier: Environment :: Web Environment
Classifier: Intended Audience :: Developers
Classifier: License :: OSI Approved :: MIT License
Classifier: Operating System :: OS Independent
Classifier: Programming Language :: Python :: 2
Classifier: Programming Language :: Python :: 3
Classifier: Topic :: Software Development :: Libraries :: Python Modules
Classifier: Topic :: System :: Systems Administration :: Authentication/Directory
Requires-Dist: pycryptodome
Requires-Dist: requests
Requires-Dist: six
Requires-Dist: tox
